GeoBay/GeoBay.py
GeoBay/__init__.py
GeoBay/common.py
GeoBay/foliumap.py
GeoBay/hydro.py
geobay-1.0.1.dist-info/licenses/LICENSE
geobay-1.0.1.dist-info/METADATA
geobay-1.0.1.dist-info/WHEEL
geobay-1.0.1.dist-info/entry_points.txt
geobay-1.0.1.dist-info/top_level.txt
geobay-1.0.1.dist-info/RECORD
