Metadata-Version: 2.4
Name: GeoBay
Version: 1.0.1
Summary: A python package for geospatial analysis and mapping
Author: Casey Shea
Author-email: Casey Shea <shea96@gmail.com>
License: MIT License
Project-URL: Homepage, https://github.com/Caseyshea96/GeoBay
Keywords: GeoBay
Classifier: Intended Audience :: Developers
Classifier: License :: OSI Approved :: MIT License
Classifier: Natural Language :: English
Classifier: Programming Language :: Python :: 3.8
Classifier: Programming Language :: Python :: 3.9
Classifier: Programming Language :: Python :: 3.10
Classifier: Programming Language :: Python :: 3.11
Classifier: Programming Language :: Python :: 3.12
Requires-Python: >=3.8
License-File: LICENSE
Requires-Dist: numpy
Requires-Dist: ipyleaflet>=0.17.0
Requires-Dist: geopandas>=0.10.0
Requires-Dist: mkdocs>=1.4.0
Requires-Dist: mkdocstrings
Requires-Dist: mkdocstrings-python
Requires-Dist: ipywidgets
Requires-Dist: earthengine-api
Requires-Dist: geemap
Provides-Extra: all
Requires-Dist: GeoBay[extra]; extra == "all"
Provides-Extra: extra
Requires-Dist: pandas; extra == "extra"
Dynamic: author
Dynamic: license-file
